intake_odbc/__init__.py
intake_odbc/_version.py
intake_odbc/intake_odbc.py
intake_odbc-0.2.0.dist-info/LICENSE
intake_odbc-0.2.0.dist-info/METADATA
intake_odbc-0.2.0.dist-info/WHEEL
intake_odbc-0.2.0.dist-info/entry_points.txt
intake_odbc-0.2.0.dist-info/top_level.txt
intake_odbc-0.2.0.dist-info/RECORD
