Metadata-Version: 2.1
Name: intake-odbc
Version: 0.2.0
Summary: ODBC plugin for Intake
Home-page: https://github.com/ContinuumIO/intake-odbc
Maintainer: Stan Seibert
Maintainer-email: sseibert@anaconda.com
License: BSD
License-File: LICENSE
Requires-Dist: intake
Requires-Dist: turbodbc
Requires-Dist: pyarrow
Requires-Dist: pandas
